hyperway/__init__.py
hyperway/_version.py
hyperway/constants.py
hyperway/edges.py
hyperway/generator.py
hyperway/ident.py
hyperway/nodes.py
hyperway/packer.py
hyperway/reader.py
hyperway/stepper.py
hyperway/tools.py
hyperway/writer.py
hyperway/graph/__init__.py
hyperway/graph/base.py
hyperway/graph/graph.py
hyperway-1.0.9.dist-info/licenses/LICENSE
hyperway-1.0.9.dist-info/METADATA
hyperway-1.0.9.dist-info/WHEEL
hyperway-1.0.9.dist-info/top_level.txt
hyperway-1.0.9.dist-info/RECORD
