Metadata-Version: 2.4
Name: hyperway
Version: 1.0.9
Summary: A graph based functional execution library. Connect functions arbitrarily through a unique API
Author-email: Strangemother <hyperway@strangemother.com>
License-Expression: MIT
Project-URL: Homepage, https://github.com/Strangemother/python-hyperway
Project-URL: Documentation, https://github.com/Strangemother/python-hyperway/tree/main/docs
Project-URL: Bug Tracker, https://github.com/Strangemother/python-hyperway/issues
Project-URL: Source Code, https://github.com/Strangemother/python-hyperway
Project-URL: Changelog, https://github.com/Strangemother/python-hyperway/blob/main/RELEASE_NOTES_v1.0.0.md
Keywords: graph,execution-engine,functional-programming,dataflow,computational-graph,workflow,pipeline
Classifier: Programming Language :: Python :: 3
Classifier: Programming Language :: Python :: 3.8
Classifier: Programming Language :: Python :: 3.9
Classifier: Programming Language :: Python :: 3.10
Classifier: Programming Language :: Python :: 3.11
Classifier: Programming Language :: Python :: 3.12
Classifier: Operating System :: OS Independent
Classifier: Development Status :: 5 - Production/Stable
Classifier: Intended Audience :: Developers
Classifier: Topic :: Software Development :: Libraries :: Python Modules
Classifier: Topic :: Scientific/Engineering
Classifier: Typing :: Typed
Requires-Python: >=3.8
License-File: LICENSE
Provides-Extra: graphviz
Requires-Dist: graphviz>=0.20; extra == "graphviz"
Provides-Extra: dev
Requires-Dist: pytest; extra == "dev"
Requires-Dist: pytest-cov; extra == "dev"
Requires-Dist: tox; extra == "dev"
Provides-Extra: docs
Requires-Dist: sphinx; extra == "docs"
Requires-Dist: sphinx-rtd-theme; extra == "docs"
Dynamic: license-file
